pydatafront/__init__.py
pydatafront/__main__.py
pydatafront/app/__init__.py
pydatafront/decorator/__init__.py
pydatafront-0.1.0.dist-info/METADATA
pydatafront-0.1.0.dist-info/WHEEL
pydatafront-0.1.0.dist-info/top_level.txt
pydatafront-0.1.0.dist-info/RECORD
