Metadata-Version: 2.1
Name: pydatafront
Version: 0.1.0
Requires-Python: >=3.8
Requires-Dist: flask
Requires-Dist: flask-cors
Requires-Dist: functions-framework (==3.*)
Requires-Dist: pyyaml (>5.1)
Requires-Dist: requests
